PyFEMP/FEM_SOLVER.py
PyFEMP/__init__.py
PyFEMP/assets/__init__.py
PyFEMP/assets/plate_with_hole/plate_with_hole_elmts.csv
PyFEMP/assets/plate_with_hole/plate_with_hole_elmts_fine.csv
PyFEMP/assets/plate_with_hole/plate_with_hole_elmts_super_fine.csv
PyFEMP/assets/plate_with_hole/plate_with_hole_nodes.csv
PyFEMP/assets/plate_with_hole/plate_with_hole_nodes_fine.csv
PyFEMP/assets/plate_with_hole/plate_with_hole_nodes_super_fine.csv
PyFEMP/elements/Elmt_BaMo_2D.py
PyFEMP/elements/Elmt_BaMo_2D_Dy.py
PyFEMP/elements/Elmt_BaMo_BaEn_Coupled_1D.py
PyFEMP/elements/LE_T1.py
PyFEMP/elements/LE_T_Q1.py
PyFEMP/elements/Laplace_Q1.py
PyFEMP/elements/T1_J2.py
PyFEMP/elements/__init__.py
PyFEMP/meshing/__init__.py
PyFEMP/meshing/mesh_1d.py
PyFEMP/meshing/mesh_2d.py
PyFEMP-0.0.9.dist-info/LICENSE
PyFEMP-0.0.9.dist-info/METADATA
PyFEMP-0.0.9.dist-info/WHEEL
PyFEMP-0.0.9.dist-info/top_level.txt
PyFEMP-0.0.9.dist-info/RECORD
