Metadata-Version: 2.1
Name: PyFEMP
Version: 0.0.9
Summary: A python FEM solver for educational purposes.
Home-page: https://git.uni-due.de/mechanik/py_femp
Author: Sascha F. Maassen
Author-email: sascha.maassen@uni-due.de
License: MIT
Project-URL: Wiki, https://git.uni-due.de/mechanik/py_femp/-/wikis/home
Platform: UNKNOWN
Classifier: Programming Language :: Python :: 3
Classifier: License :: OSI Approved :: MIT License
Classifier: Operating System :: OS Independent
Requires-Python: >=3.6
License-File: LICENSE
Requires-Dist: numpy
Requires-Dist: matplotlib
